kstar/__init__.py
kstar/calculate.py
kstar/config.py
kstar/configuration.json
kstar/helpers.py
kstar/mapping.py
kstar/plot.py
kstar/prune.py
kstar/RESOURCE_FILES/HumanPhosphoProteome.csv
kstar/RESOURCE_FILES/citations_compendia.txt
kstar/RESOURCE_FILES/humanProteome.fasta
kstar/RESOURCE_FILES/readme.txt
kstar/RESOURCE_FILES/reference_info.json
kstar/analysis/__init__.py
kstar/analysis/coverage.py
kstar/analysis/interactions.py
kstar/analysis/kinase_MI.py
kstar/dataset_processing/__init__.py
kstar/dataset_processing/accessions.py
kstar/dataset_processing/peptides.py
kstar/random_experiments/__init__.py
kstar/random_experiments/calculate_fpr.py
kstar/random_experiments/generate_random_experiments.py
kstar/random_experiments/pregenerate.py
kstar-1.1.0.dist-info/licenses/LICENSE
kstar-1.1.0.dist-info/METADATA
kstar-1.1.0.dist-info/WHEEL
kstar-1.1.0.dist-info/top_level.txt
kstar-1.1.0.dist-info/RECORD
