Metadata-Version: 2.4
Name: kstar
Version: 1.1.0
Summary: KSTAR: Kinase-Substrate Transfer to Activity Relationships
Home-page: https://github.com/NaegleLab/KSTAR
Author: Naegle Lab
Author-email: kmn4mj@virginia.edu
License: GNU General Public License v3
Project-URL: Homepage, https://github.com/NaegleLab/KSTAR
Project-URL: Documentation, https://naeglelab.github.io/KSTAR/
Keywords: kinase,phosphoproteomics,bioinformatics,proteomics,kinase activity inference
Classifier: Programming Language :: Python :: 3
Classifier: Intended Audience :: Science/Research
Classifier: Operating System :: OS Independent
Requires-Python: >=3.9
License-File: LICENSE
Requires-Dist: pandas>=2.1
Requires-Dist: numpy>=1.26
Requires-Dist: scipy>=1.11
Requires-Dist: matplotlib>=3.8
Requires-Dist: seaborn>=0.13
Requires-Dist: requests
Requires-Dist: fpdf2>=2.5
Requires-Dist: tqdm
Dynamic: author
Dynamic: author-email
Dynamic: classifier
Dynamic: description
Dynamic: home-page
Dynamic: keywords
Dynamic: license
Dynamic: license-file
Dynamic: project-url
Dynamic: requires-dist
Dynamic: requires-python
Dynamic: summary
